gesha/__init__.py
gesha/conf.py
gesha/mixins.py
gesha/py.typed
gesha/types.py
gesha/urls.py
gesha/views.py
gesha/static/gesha/dist/js/django-gesha.bundle.min.js
gesha/static/gesha/dist/js/django-gesha.bundle.min.js.map
gesha/templatetags/__init__.py
gesha/templatetags/gesha.py
django_gesha-0.1a5.dist-info/LICENSE
django_gesha-0.1a5.dist-info/METADATA
django_gesha-0.1a5.dist-info/WHEEL
django_gesha-0.1a5.dist-info/top_level.txt
django_gesha-0.1a5.dist-info/RECORD
