Metadata-Version: 2.1
Name: django-gesha
Version: 0.1a5
Summary: JavaScript utilities for Django projects.
Author-email: elyas <elyas@ely.as>
License: MIT
Project-URL: Documentation, https://django-gesha.readthedocs.io/en/latest/
Project-URL: Issue Tracker, https://github.com/ely-as/django-gesha/issues
Project-URL: Source, https://github.com/ely-as/django-gesha
Keywords: django,javascript,typescript
Classifier: Development Status :: 3 - Alpha
Classifier: Intended Audience :: Developers
Classifier: License :: OSI Approved :: MIT License
Classifier: Programming Language :: JavaScript
Classifier: Programming Language :: Python :: 3
Classifier: Programming Language :: Python :: 3 :: Only
Classifier: Programming Language :: Python :: 3.8
Classifier: Programming Language :: Python :: 3.9
Classifier: Programming Language :: Python :: 3.10
Classifier: Programming Language :: Python :: 3.11
Classifier: Typing :: Typed
Classifier: Framework :: Django
Classifier: Framework :: Django :: 2.2
Classifier: Framework :: Django :: 3.0
Classifier: Framework :: Django :: 3.1
Classifier: Framework :: Django :: 3.2
Classifier: Framework :: Django :: 4.0
Classifier: Framework :: Django :: 4.1
Classifier: Framework :: Django :: 4.2
Requires-Python: >=3.8
License-File: LICENSE
Requires-Dist: Django
Provides-Extra: doc
Requires-Dist: mkdocs ; extra == 'doc'
Requires-Dist: mkdocs-material ; extra == 'doc'
Provides-Extra: test
Requires-Dist: black ; extra == 'test'
Requires-Dist: beautifulsoup4 ; extra == 'test'
Requires-Dist: lxml ; extra == 'test'
Requires-Dist: mypy ; extra == 'test'
Requires-Dist: pytest (>=7) ; extra == 'test'
Requires-Dist: pytest-cov (>=4.1) ; extra == 'test'
Requires-Dist: pytest-django ; extra == 'test'
Requires-Dist: ruff ; extra == 'test'
Requires-Dist: types-beautifulsoup4 ; extra == 'test'
Requires-Dist: uvicorn ; extra == 'test'
